hdk_pkg/__init__.py
hdk_pkg/critest.py
hdk_pkg/backtest/__init__.py
hdk_pkg/backtest/func_Momentum.py
hdk_pkg/backtest/func_Status.py
hdk_pkg/plotting/__init__.py
hdk_pkg/plotting/func_plot_type1.py
hdk_pkg/process/__init__.py
hdk_pkg/process/func_1min2day.py
hdk_pkg/process/func_BarCount.py
hdk_pkg/process/func_BarHA.py
hdk_pkg/process/func_BarPS.py
hdk_pkg/process/func_ChangeGranularity.py
hdk_pkg/process/func_WVF.py
hdk_pkg/sampledata/__init__.py
hdk_pkg/sampledata/data.py
hdk_pkg/sampledata/eth_kline.csv
hdk_pkg_cri-0.0.8.dist-info/LICENSE
hdk_pkg_cri-0.0.8.dist-info/METADATA
hdk_pkg_cri-0.0.8.dist-info/WHEEL
hdk_pkg_cri-0.0.8.dist-info/top_level.txt
hdk_pkg_cri-0.0.8.dist-info/RECORD
