Metadata-Version: 2.1
Name: hdk-pkg-cri
Version: 0.0.8
Summary: A small example package for CRI PMT test.
Home-page: https://github.com/HDKidd/hdk-pkg-cri
Author: He Dekun
Author-email: hede0001@e.ntu.edu.sg
License: UNKNOWN
Platform: UNKNOWN
Classifier: Programming Language :: Python :: 3
Classifier: License :: OSI Approved :: MIT License
Classifier: Operating System :: OS Independent
Requires-Python: >=3.6
